databonsai/__init__.py
databonsai/categorize/__init__.py
databonsai/categorize/base_categorizer.py
databonsai/categorize/multi_categorizer.py
databonsai/llm_providers/__init__.py
databonsai/llm_providers/anthropic_provider.py
databonsai/llm_providers/llm_provider.py
databonsai/llm_providers/ollama_provider.py
databonsai/llm_providers/openai_provider.py
databonsai/transform/__init__.py
databonsai/transform/base_transformer.py
databonsai/transform/extract_transformer.py
databonsai/utils/__init__.py
databonsai/utils/apply.py
databonsai/utils/logs.py
tests/__init__.py
tests/test_categorization.py
databonsai-0.8.0.dist-info/LICENSE
databonsai-0.8.0.dist-info/METADATA
databonsai-0.8.0.dist-info/WHEEL
databonsai-0.8.0.dist-info/top_level.txt
databonsai-0.8.0.dist-info/RECORD
