Metadata-Version: 2.1
Name: databonsai
Version: 0.8.0
Summary: A package for cleaning and curating data with LLMs
Home-page: https://github.com/databonsai/databonsai
Author: Alvin Ryanputra
Author-email: databonsai.ai@gmail.com
Classifier: Development Status :: 3 - Alpha
Classifier: Intended Audience :: Developers
Classifier: License :: OSI Approved :: MIT License
Classifier: Programming Language :: Python :: 3.8
Classifier: Programming Language :: Python :: 3.9
Classifier: Programming Language :: Python :: 3.10
Classifier: Programming Language :: Python :: 3.11
Classifier: Programming Language :: Python :: 3.12
License-File: LICENSE
Requires-Dist: openai
Requires-Dist: anthropic
Requires-Dist: tenacity
Requires-Dist: python-dotenv
Requires-Dist: pydantic
Requires-Dist: ollama
